{
    "addr": "Los Angeles, CA", 
    "title": "YVES BARON LE TENOR LOS ANGELES TOUR", 
    "url": "http://www.eventbrite.com/e/yves-baron-le-tenor-los-angeles-tour-tickets-18663781874?aff=ebrowse", 
    "location": "Los Angeles, CA", 
    "starttime": "2016-04-03T19:00:00-07:00", 
    "endtime": "2016-04-23T22:00:00-07:00", 
    "categories": [
        "Music", 
        "Concert or Performance"
    ], 
    "desc": "YVES BARON LE TENOR ON TOUR IN LOS ANGELES  ? ?Dear Sir/Madam, ? ? ?I am proud to introduce: ?YVES BARON LE TENOR! ? ?http://yvesbaroninvites.unblog.fr https://www.youtube.com/watch?v=Sg8nLK3OaIA ? ? ? ?A Worldwide performer from PARIS & BANGKOK. ? ?1500 international shows! ? ?4 continents! (Europe-Asia-Africa-USA) ? ? ? ?TESTIMONIALS ? ??Powerful!? (Le Lounge Los Angeles) ? ??Sensational!? (Persian TV) ? ??Charismatic!? (Radio Lora Munich) ? ? ? ?Also known as Le Tenor, Baron is a multi-talented Thai-French singer ? who learned to play classical guitar? ??? with??? maestro Jean-Luc Derhy. He is a master vocal coach at Bangkok's Superstar Academy and his live? ?performances have received rave reviews. Baron composed his first ?songs as a teenager and after exposure on ?the Parisian night scene with DJ Tokoto Grimblat and nightclub owner Addy Bakhtiar went on to become one of ?Europe night clubs top promoters. After years perfecting his art, today Baron combines his incredibly rich tenor ?vocals with amazing guest stars , much to the delight of his audience ? ? ? ?SHOWS PROPOSALS : ? ?YVES BARON LE TENOR SOLO ? ?YVES BARON INVITES...( with Guest stars ) ? ?BOOKINGS :  Yvesbarontenor@gmail.com ? ? ? ? ? ? ? ? ? ? ? ? ? ? ? ? ? ? ? ? ? MEDIA APPEARANCES"
}