{
    "addr": "Broad Sanctuary. Westminster. London SW1P 3EE GB", 
    "title": "THINK Cloud for Government 2016", 
    "url": "http://www.eventbrite.co.uk/e/think-cloud-for-government-2016-tickets-17222988422?aff=ebrowse", 
    "location": "London, United Kingdom", 
    "starttime": "2016-03-22T08:30:00+00:00", 
    "endtime": "2016-03-22T17:00:00+00:00", 
    "categories": [
        "Government \\u0026 Politics", 
        "Conference"
    ], 
    "desc": "Welcome to the THINK Cloud for Government ticket registration page. Now in its fifth successful year, the event formally know as Think G-Cloud provides the best opportunity for the public sector to engage with the latest developments in this vital and ever-growing area. For further information surrounding this must-attend conference please visit our homepage at www.thinkcloudforgovernment.com"
}