{
    "addr": "London E17 6HE GB", 
    "title": "Diwali Celebration 2015", 
    "url": "http://www.eventbrite.co.uk/e/diwali-celebration-2015-tickets-18136791632?aff=ebrowse", 
    "location": "London, United Kingdom", 
    "starttime": "2015-11-27T19:00:00+00:00", 
    "endtime": "2015-11-27T22:30:00+00:00", 
    "categories": [
        "Music", 
        "Concert or Performance"
    ], 
    "desc": "We will be celebrating the vibrant and colourful festival of Diwali at?the Assembly Hall at the end of November which?is always a great experience for all?the family.? As well as the wonderful?music and entertainment, there will be a?short firework display?and hot food on sale. Please note:  If you can no longer attend, please cancel your ticket and?free up the space for another person. Check your confirmation email for instructions or  click here If this event sells out, you can add yourself to the waitlist and you will be contacted if a space becomes available."
}