{
    "addr": "815 Willis Ave Albertson, NY 11507", 
    "title": "Paint Night- SPIKED Hot Cocoa & Vintage Holiday Painting Da Angelo's Restaurant", 
    "url": "http://www.eventbrite.com/e/paint-night-spiked-hot-cocoa-vintage-holiday-painting-da-angelos-restaurant-tickets-19410721992?aff=ebrowse", 
    "location": "Albertson, NY", 
    "starttime": "2015-12-10T19:00:00-05:00", 
    "endtime": "2015-12-10T21:00:00-05:00", 
    "desc": "You will be painting \"Vintage Holiday\" Enjoy? delicious Italian Struffoli? while working on \"Vintage Holiday.\" ?Stimulate your senses while creating your masterpiece! YUMMI Studios combines simple step-by-step classes, some of your favorite music, edibles for a multi-sensory art experience!? Can?t draw or paint? Great! No experience necessary, ?it?s easy and stress-free! Our instructor will guide you step-by-step through the night?s featured project.? All artistic skill levels are welcome! ? Come down to our Huntington studio or have us come to you for your own private event!"
}