{
    "addr": "361 West 125th Street, 1st Floor. Room 1A. New York, NY 10027", 
    "title": "Website Fundamentals, Upper Manhattan, 12/1/15", 
    "url": "http://www.eventbrite.com/e/website-fundamentals-upper-manhattan-12115-registration-18650818099?aff=ebrowse", 
    "location": "New York, NY", 
    "starttime": "2015-12-01T17:30:00-05:00", 
    "endtime": "2015-12-01T19:30:00-05:00", 
    "desc": "Small Business Digital Toolkit: Website Fundamentals Make your business known on the World Wide Web!  Websites are a great way to inform customers about your products and services. In this high-energy, fast-moving course, you?ll learn basic information needed to develop a website that best suits your business needs. We?ll guide you through how to use your website to build your brand and sell your products and services. You?ll also hear about the various steps involved with getting your website up and running. You?ll leave this course feeling energized, and prepared to take action on creating your business? website. You will learn about:"
}