{
    "addr": " 66 Fifth Avenue New York, New York 10003", 
    "title": "When Free Speech and Democracy Conflict: Campaign Finance in the Age of Citizens United - A Talk by Jonathan Soros", 
    "url": "http://www.eventbrite.com/e/when-free-speech-and-democracy-conflict-campaign-finance-in-the-age-of-citizens-united-a-talk-by-tickets-19363765544?aff=ebrowse", 
    "location": "New York, United States", 
    "starttime": "2015-12-03T17:00:00-05:00", 
    "endtime": "2015-12-03T19:00:00-05:00", 
    "categories": [
        "Other", 
        "Seminar or Talk"
    ], 
    "desc": "Robert L. Heilbroner Center for Capitalism Studies ?presents? \"When Free Speech and Democracy Conflict: Campaign Finance in the Age of Citizens United\" Jonathan Soros, Senior Fellow, Roosevelt Institute? In conversation with: Reception to follow."
}