{
    "addr": "235 West 23rd Street New York, NY 10011", 
    "title": "#ShortyStories with Viners Chris Melberger & Shan Dodd", 
    "url": "http://www.eventbrite.com/e/shortystories-with-viners-chris-melberger-shan-dodd-tickets-19361980204?aff=ebrowse", 
    "location": "New York, NY", 
    "starttime": "2015-12-08T19:00:00-05:00", 
    "endtime": "2015-12-08T20:30:00-05:00", 
    "categories": [
        "Other", 
        "Seminar or Talk"
    ], 
    "desc": "From the creators of the? Shorty Awards , join us for an evening of cocktails, social media and stories!?#ShortyStories is a new monthly event series featuring an influencer or content creator who is making a career out of the internet. ? On December 8th at 7pm, come hear the story of Viners  Chris Melberger  &  Shan Dodd .  Hear how they got their start in the digital space, how Vine brought them together and what?s next for these neat dudes. ? Big thank you to Wix for hosting our event this month!"
}