{
    "addr": "99 Madison Ave New York, NY 10016", 
    "title": "Hive NYC Holiday Party", 
    "url": "https://www.eventbrite.com/e/hive-nyc-holiday-party-tickets-19661860153?aff=ebrowse", 
    "location": "", 
    "starttime": "2015-12-17T19:00:00-05:00", 
    "endtime": "2015-12-17T21:00:00-05:00", 
    "categories": [
        "New York, NY Events", 
        "Party", 
        "Community"
    ], 
    "desc": "Celebrate with your Hive NYC community! \n Please RSVP so we know how many people to expect. \n Food and drinks will be provided :) \n More details to come!"
}