{
    "addr": "641 West 50th Street New York, NY 10019", 
    "title": "NYC Urban Professionals Holiday Party with a Purpose", 
    "url": "https://www.eventbrite.com/e/nyc-urban-professionals-holiday-party-with-a-purpose-tickets-19563017512?aff=ebrowse", 
    "location": "", 
    "starttime": "2015-12-16T17:30:00-05:00", 
    "endtime": "2015-12-16T22:00:00-05:00", 
    "categories": [
        "New York, NY Events", 
        "Party", 
        "Charity & Causes"
    ], 
    "desc": "Black Urban Professionals \n Holiday Party with a Purpose \n \n $25?\"early bird\" online payment, now - 12/9 . \n $30 ?online payment 12/10 - 12/14, noon cut-off \n $40? at the door. \n ? *Complimentary Hors D?oeuvers* \n Don't miss this rare opportunity to interact with multiple?black?professional?organizations at one exclusive event! Proceeds from this year's event will go to the?March of Dimes?dedicated to improving the health of babies - in memory of? Jonah Daniel Lodge Bing .? As powerfully illustrated in? this video clip from Unnatural Causes , Black babies are 2-3 times more likely not to make it to their first birthday as compared to other babies.? (Note: Funds raised will go towards the New York City area and the Campaign for Black Babies managed by the National Birth Equity Collaborative.)? \n Join us as we network with other discerning?professionals?across a variety of industries and donate to a great cause.? Representatives from each organization will be present if you would like to learn more and get involved. \n Music by?DJ Jon Quick?and?DJ Spider \n Hosted by :? \n Avant-Garde Network \n Black Data Processing Association? (BDPA) \n Black Ivy League Events \n Metropolitan Black Bar Association ?(MBBA) \n National Association of Black Accountants? (NABA) \n National Black MBA Association? (NBMBAA) \n National Society of Black Engineers? (NSBE) \n New York Empire State Medical Association ?(NYESMA) \n New York Urban League Young Professionals? (NYULYP) \n One Hundred Black Men \n \n ? \n \n \n \n \n Representatives from each organization will be present if you would like to learn more and get involved. \n \n \n Hope to see you there!"
}