{
    "addr": "1535 Broadway, . 8th Floor, Liberty Room,. New York, NY 10036", 
    "title": "BEI Investment Forum", 
    "url": "https://www.eventbrite.com/e/bei-investment-forum-tickets-19715786448?aff=ebrowse", 
    "location": "", 
    "starttime": "2015-12-09T07:00:00-05:00", 
    "endtime": "2015-12-09T23:00:00-05:00", 
    "categories": [
        "New York, NY Events", 
        "Other", 
        "Business"
    ], 
    "desc": "Venue: Marriott Marquis Hotel, 8th Floor, Times Square, New York, NY 10036. Below event in addition to Event Image. \n Wednesday, December 09, 2015, 10pm - 11pm - Concert/Fundraiser for victims of Terrorism, including kidnapped Chibok Girls in   Nigeria. ? \n Tickets starts at $2,000(two-thousand US Dollars) each. Sponsorship Opportunities available. Contact Soji Adeyemi at (646)258-7550 and email:  binvestmentforum2015@gmail.com \n Limited tickets at $2,000 each and the remaining tickets will be auctioned so purchase tickets early. \n ? \n FAQs \n ? \n Are there ID requirements or an age limit to enter the event? \n All attendees must be older than?21 years except speakers, performers and selected Celebrities like Justin Bieber. \n ? \n What are my transport/parking options getting to the event? \n Attendees must find their own parking around Times Square. It is Highly recommended you take taxi or public transportation or chauvered vehicle to Times Square. \n ? \n What can/can't I bring to the event? \n For security reasons, large bags are not allowed and all bags and wallets will be searched before entering the venue. \n ? \n Where can I contact the organizer with any questions? \n Call Soji at (646)258-7550 or email  binvestmentforum2015@gmail.com \n Is my registration/ticket transferrable? \n No. Tickets are not transferable. \n ? \n Can I update my registration information? \n No \n ? \n Do I have to bring my printed ticket to the event? \n YES. \n ? \n What is the refund policy? \n No refunds. \n ? \n The name on the registration/ticket doesn't match the attendee. Is that okay? \n No"
}