{
    "addr": " New York City,  New York", 
    "title": "PMP Exam Prep Class - New York City, New York", 
    "url": "http://www.eventbrite.com/e/pmp-exam-prep-class-new-york-city-new-york-tickets-17465178820?aff=ebrowse", 
    "location": "New York City,  New York", 
    "starttime": "2015-12-14T08:30:00-05:00", 
    "endtime": "2015-12-17T18:00:00-05:00", 
    "categories": [
        "Other", 
        "Class, Training, or Workshop"
    ], 
    "desc": "PMP & CAPM Exam Prep Class December 14 through December 17, ?Monday through Thursday, 8:30 a.m. to 6:00 p.m. Location:??New York City, New York PMP and CAPM certification exam training boot camp class includes 100% live and interactive in-person instruction earning 35 eligible contact hours and completion certificate. Students get the print edition of the  PMBOK? Guide , student course book and learning aids (checklists, formula worksheets, examples, exercises, etc.), online PMP practice exam tests with thousands of questions and answers (with explanations), invites to attend for free our other training classes, individual sessions, and Webinars as extra study opportunities, help with PMI application, refreshments, and free parking. More :?  https://www.projectweavers.com/pmp-exam-prep-course-boot-camp-new-york-city FAQs :?  https://www.projectweavers.com/faq/ Terms & Conditions :?  https://www.projectweavers.com/terms-and-conditions/"
}