{
    "addr": "725 California Avenue Santa Monica, CA 90403", 
    "title": "Start Right, Stay Connected Couple Workshop - March 5, 2016", 
    "url": "http://www.eventbrite.com/e/start-right-stay-connected-couple-workshop-march-5-2016-tickets-17701659139?aff=ebrowse", 
    "location": "Santa Monica, CA", 
    "starttime": "2016-03-05T09:00:00-08:00", 
    "endtime": "2016-03-05T18:00:00-08:00", 
    "desc": "Engaged?... Newly married?... Thinking of going in that direction? ? ?Start Right, Stay Connected? ? ? is a one-day program designed to provide couples with the knowledge and tools to navigate the challenges of marriage.? In a fun and dynamic setting, you will learn to more effectively communicate with your partner, deepen your connection and create a shared vision for your relationship."
}