{
    "addr": "5400 West Century Boulevard. Los Angeles, CA 90045", 
    "title": "FlipFest LA", 
    "url": "http://www.eventbrite.com/e/flipfest-la-tickets-18799000316?aff=ebrowse", 
    "location": "Los Angeles, CA", 
    "starttime": "2015-11-21T08:00:00-08:00", 
    "endtime": "2015-11-21T17:00:00-08:00", 
    "desc": "Rehab Expert Dave Seymour. He is a rags to riches story who will motivate you. He now races to rehab properties. He'll teach you how to flip 'em fast and make money in LA.  have over a decade of professional real estate experience and have been featured in national print publications, online media outlets, and  . The dynamic couple has created unique strategies that give them an edge in today?s real estate market. ?   5400 West Century Boulevard Los Angeles, CA 90045 Saturday, November 21, 2015 from 8:00 AM to 5:00 PM (PST) ? ? ? ? Attendees must be 18 years or older. ? Please bring a pen & paper to take lots of notes! ?And don't forget your business cards. ? ? Yes. You/They can do this at registration the day of the show. ? Yes. You can do this at registration the day of the show. ? Per our company policy, there are NO refunds. ? Yes. You can update your registration info the day of the show at the registration desk. ? Dress code is business casual."
}