{
    "addr": "Student Center Irvine, CA 92697", 
    "title": "Orange County Private School Association Fair", 
    "url": "http://www.eventbrite.com/e/orange-county-private-school-association-fair-tickets-18520397006?aff=ebrowse", 
    "location": "Irvine, CA", 
    "starttime": "2016-01-24T13:00:00-08:00", 
    "endtime": "2016-01-24T16:00:00-08:00", 
    "desc": "UCI Student Center University of California, Irvine Irvine, CA 92697 Parking available in the adjacent Student Center Parking Structure (corner of West Peltason Dr & Pereira Dr ?? Join us for our 6th Annual Preschool ? 12th Grade Fair to preview 70+ renowned preschools, elementary/middle schools, and high schools. From year to year, this fair has provided OC families an opportunity to learn about the various private school options by talking directly to representatives from each school. This is your chance to: Sign up today! Registration is free."
}