{
    "addr": "11200 Baseline Road Rancho Cucamonga, CA 91701", 
    "title": "IE 3rd Annual Thank A Sheros Event", 
    "url": "http://www.eventbrite.com/e/ie-3rd-annual-thank-a-sheros-event-tickets-18541997614?aff=ebrowse", 
    "location": "Rancho Cucamonga, CA", 
    "starttime": "2016-03-16T10:00:00-07:00", 
    "endtime": "2016-03-16T15:00:00-07:00", 
    "desc": "This event is in honor of Women's Military History Week to?promote positive images provide resources and public awareness of women?s contributions from all branches and eras of service, recognizing the tremendous contributions made by all military women to this  N ation ,  the  S tate ,  and Communities The Women Veterans Unity Group  in partnership with the Inland Empire Women Veterans Collaborative  will have the honor to host the  Inland Empire?3rd  Annual  Thank A S heros  Event during Women?s Military History Week  the third week in March .  The Event Theme is ?Addressing Women Gender-Specific Resources?.  Our purpose is to serve and empower the Women Veteran Communities and perform outreach to improve women veterans awareness of eligibility for communities,  education,  county, state ,  veteran services and benefits. This event will allow the women veteran,  other service providers, and communities to participate in a series of events during the 3 rd  week in March to show our appreciation for women military service to our country. We will include informative and  inspirational women speakers"
}