{
    "addr": "Ealing Green. London.  W5 5EP GB", 
    "title": "Writing and Selling Thriller Screenplays with Lucy V Hay", 
    "url": "http://www.eventbrite.co.uk/e/writing-and-selling-thriller-screenplays-with-lucy-v-hay-tickets-18017874949?aff=ebrowse", 
    "location": "", 
    "starttime": "2015-11-28T09:30:00+00:00", 
    "endtime": "2015-11-29T17:30:00+00:00", 
    "categories": [
        "Film, Media \\u0026 Entertainment", 
        "Class, Training, or Workshop"
    ], 
    "desc": ""
}